gearsclient/__init__.py
gearsclient/redisgears_builder.py
gearsclient-1.0.2.dist-info/LICENSE
gearsclient-1.0.2.dist-info/WHEEL
gearsclient-1.0.2.dist-info/METADATA
gearsclient-1.0.2.dist-info/RECORD
