Metadata-Version: 2.1
Name: gearsclient
Version: 1.0.2
Summary: RedisGears Python Client
License: BSD-3-Clause
Keywords: Redis JSON Extension
Author: RedisLabs
Author-email: oss@redislabs.com
Requires-Python: >=3.6,<4.0
Classifier: Development Status :: 5 - Production/Stable
Classifier: Intended Audience :: Developers
Classifier: License :: OSI Approved :: BSD License
Classifier: Operating System :: OS Independent
Classifier: Programming Language :: Python
Classifier: Programming Language :: Python :: 3
Classifier: Programming Language :: Python :: 3.10
Classifier: Programming Language :: Python :: 3.6
Classifier: Programming Language :: Python :: 3.7
Classifier: Programming Language :: Python :: 3.8
Classifier: Programming Language :: Python :: 3.9
Classifier: Topic :: Database
Requires-Dist: cloudpickle (>=1.6.0,<2.0.0)
Requires-Dist: redis (==3.5.3)
Requires-Dist: six (>=1.16.0,<2.0.0)
Project-URL: repository, https://github.com/RedisGears/redisgears-py
Project-URL: url, https://redisgears.io
